xpt/__init__.py
xpt/hello.py
xpt-0.0.1.dist-info/LICENSE
xpt-0.0.1.dist-info/METADATA
xpt-0.0.1.dist-info/WHEEL
xpt-0.0.1.dist-info/top_level.txt
xpt-0.0.1.dist-info/RECORD
