Metadata-Version: 2.1
Name: xpt
Version: 0.0.1
Summary: Pytorch with XLA
Home-page: https://github.com/alibaba
Author: AngWang
Author-email: wangang.wa@alibaba-inc.com
License: Apache License 2.0
Platform: UNKNOWN
Classifier: Programming Language :: Python :: 3
Classifier: Operating System :: OS Independent
Requires-Python: >=3.6
License-File: LICENSE
